<package>
  <description brief="soem_core">

     SOEM is an open source EtherCAT master library written in c. Its
     primary target is Linux but can be adapted to other OS and
     embedded systems. (http://developer.berlios.de/projects/soem/)

     This package contains the original soem c code provided by the Technische Universiteit Eindhoven.

  </description>
  <author>Arthur Ketels and M.J.G. van den Molengraft; packaged by Ruben Smits</author>
  <license>GPL+linking exception</license>
  <review status="unreviewed" notes=""/>
  <url>http://developer.berlios.de/projects/soem</url>

  <export>
    <cpp cflags="-I${prefix}/build/soem_core/src" lflags="-Wl,-rpath,${prefix}/lib -L${prefix}/lib -lsoem_core"/>
  </export>
</package>


